metagentorch/__init__.py
metagentorch/_modidx.py
metagentorch/art.py
metagentorch/bio.py
metagentorch/core.py
metagentorch/wandb.py
metagentorch/cnn_virus/__init__.py
metagentorch/cnn_virus/architecture.py
metagentorch/cnn_virus/data.py
metagentorch/cnn_virus/utils.py
metagentorch-0.0.1.dist-info/LICENSE
metagentorch-0.0.1.dist-info/METADATA
metagentorch-0.0.1.dist-info/WHEEL
metagentorch-0.0.1.dist-info/entry_points.txt
metagentorch-0.0.1.dist-info/top_level.txt
metagentorch-0.0.1.dist-info/RECORD
