Metadata-Version: 2.1
Name: metagentorch
Version: 0.0.1
Summary: Set of tools used for metagenomics research project, using keras and pytorch
Home-page: https://github.com/vtecftwy/metagentorch
Author: Charlier
Author-email: github@procurasia.com
License: Apache Software License 2.0
Keywords: nbdev jupyter notebook python
Classifier: Development Status :: 4 - Beta
Classifier: Intended Audience :: Science/Research
Classifier: Natural Language :: English
Classifier: Programming Language :: Python :: 3.10
Classifier: Programming Language :: Python :: 3.11
Classifier: Programming Language :: Python :: 3.12
Classifier: License :: OSI Approved :: Apache Software License
Requires-Python: >=3.10
License-File: LICENSE
Requires-Dist: eccore
Requires-Dist: fastcore
Requires-Dist: matplotlib
Requires-Dist: numpy
Requires-Dist: pandas
Requires-Dist: tqdm
Requires-Dist: ipywidgets
Requires-Dist: keras (==3.8)
Requires-Dist: torch (==2.5)
Provides-Extra: dev
Requires-Dist: nbdev ; extra == 'dev'
Requires-Dist: wandb ; extra == 'dev'
